aws_dynamodb_parser/__init__.py
aws_dynamodb_parser/utils.py
tests/__init__.py
tests/test_parser.py
aws_dynamodb_parser-0.1.3.dist-info/LICENSE
aws_dynamodb_parser-0.1.3.dist-info/METADATA
aws_dynamodb_parser-0.1.3.dist-info/WHEEL
aws_dynamodb_parser-0.1.3.dist-info/top_level.txt
aws_dynamodb_parser-0.1.3.dist-info/RECORD
