Metadata-Version: 2.1
Name: aws-dynamodb-parser
Version: 0.1.3
Summary: AWS DynamoDB utility for parsing DynamoDB responses
Home-page: https://github.com/gridsmartercities/aws-dynamodb-parser
Author: Grid Smarter Cities
Author-email: open-source@gridsmartercities.com
License: MIT
Keywords: aws lambda decorator
Platform: UNKNOWN
Classifier: Intended Audience :: Developers
Classifier: Development Status :: 3 - Alpha
Classifier: Programming Language :: Python :: 3
Classifier: License :: OSI Approved :: MIT License
Classifier: Operating System :: OS Independent
Classifier: Natural Language :: English
License-File: LICENSE
